mkdocs_ab6459/404.html
mkdocs_ab6459/__init__.py
mkdocs_ab6459/contents_page.html
mkdocs_ab6459/header.html
mkdocs_ab6459/main.html
mkdocs_ab6459/mkdocs_theme.yml
mkdocs_ab6459/sidebar.html
mkdocs_ab6459/css/admonition.css
mkdocs_ab6459/css/body.css
mkdocs_ab6459/css/containers.css
mkdocs_ab6459/css/content.css
mkdocs_ab6459/css/header.css
mkdocs_ab6459/css/lab_activities.css
mkdocs_ab6459/css/mermaid.css
mkdocs_ab6459/css/sidebar.css
mkdocs_ab6459/css/variables.css
mkdocs_ab6459/css/source_code/containers.css
mkdocs_ab6459/css/source_code/github-dark.css
mkdocs_ab6459/css/source_code/github-dark.min.css
mkdocs_ab6459/css/source_code/github.css
mkdocs_ab6459/css/source_code/github.min.css
mkdocs_ab6459/images/logo.svg
mkdocs_ab6459/images/phoenix.svg
mkdocs_ab6459/images/favicon/apple-touch-icon.png
mkdocs_ab6459/images/favicon/favicon-96x96.png
mkdocs_ab6459/images/favicon/favicon.ico
mkdocs_ab6459/images/favicon/favicon.svg
mkdocs_ab6459/images/favicon/web-app-manifest-192x192.png
mkdocs_ab6459/images/favicon/web-app-manifest-512x512.png
mkdocs_ab6459/js/lab_activity_toggle.js
mkdocs_ab6459/js/navigation_toggle.js
mkdocs_ab6459/js/theme_font_toggle.js
mkdocs_ab6459-1.1.0.dist-info/METADATA
mkdocs_ab6459-1.1.0.dist-info/WHEEL
mkdocs_ab6459-1.1.0.dist-info/entry_points.txt
mkdocs_ab6459-1.1.0.dist-info/top_level.txt
mkdocs_ab6459-1.1.0.dist-info/RECORD
