Metadata-Version: 2.4
Name: mkdocs_ab6459
Version: 1.1.0
Summary: A custom theme for Coventry University modules.
Home-page: https://github.coventry.ac.uk/ab6459/mkdocs_ab6459
Author: Ian Cornelius
Author-email: ab6459@coventry.ac.uk
License: MIT
Classifier: License :: OSI Approved :: MIT License
Classifier: Topic :: Documentation
Classifier: Topic :: Text Processing
Requires-Dist: mkdocs
Dynamic: author
Dynamic: author-email
Dynamic: classifier
Dynamic: description-content-type
Dynamic: home-page
Dynamic: license
Dynamic: requires-dist
Dynamic: summary
